[
  {
    "userId": "f72a008e-b6c8-4f0b-912b-a33054e3afbc",
    "createdDate": "2015-09-14 02:00:01-0600",
    "email": "lucie_kerluke+sampleuser@killrvideo.com",
    "firstName": "Lucie",
    "lastName": "Kerluke"
  },
  {
    "userId": "6a38fae2-ee42-4a39-a30f-7894fbe6a043",
    "createdDate": "2015-09-17 17:38:01-0600",
    "email": "rosso'conner+sampleuser@killrvideo.com",
    "firstName": "Ross",
    "lastName": "O'Conner"
  },
  {
    "userId": "1438150b-9923-4ea8-be4b-bb1f5b8953bb",
    "createdDate": "2015-09-09 17:07:10-0600",
    "email": "kathleen_mcclure+sampleuser@killrvideo.com",
    "firstName": "Kathleen",
    "lastName": "McClure"
  },
  {
    "userId": "7be7b7cc-20a3-4759-ac2e-c3cf6ae5e4cd",
    "createdDate": "2015-09-03 18:00:02-0600",
    "email": "jimmie_carroll+sampleuser@killrvideo.com",
    "firstName": "Jimmie",
    "lastName": "Carroll"
  },
  {
    "userId": "2858cf98-c580-4b03-8aff-d5aa2c0a476f",
    "createdDate": "2015-09-14 00:00:02-0600",
    "email": "prudence_hodkiewicz+sampleuser@killrvideo.com",
    "firstName": "Prudence",
    "lastName": "Hodkiewicz"
  },
  {
    "userId": "05824998-92d6-4b3c-adef-cb38258bbd51",
    "createdDate": "2015-08-28 17:08:47-0600",
    "email": "dominic.jones+sampleuser@killrvideo.com",
    "firstName": "Dominic",
    "lastName": "Jones"
  },
  {
    "userId": "853b3f42-f4dc-4c76-9a5b-2cdb24dd7762",
    "createdDate": "2015-09-03 16:00:02-0600",
    "email": "sandra_mosciski+sampleuser@killrvideo.com",
    "firstName": "Sandra",
    "lastName": "Mosciski"
  },
  {
    "userId": "20fd8e8e-529c-4d5c-9ce4-cefad25e874c",
    "createdDate": "2015-08-31 12:00:02-0600",
    "email": "dusty.schmidt+sampleuser@killrvideo.com",
    "firstName": "Dusty",
    "lastName": "Schmidt"
  },
  {
    "userId": "16eddb0f-350d-436d-ad46-47d9047475b3",
    "createdDate": "2015-09-16 00:00:04-0600",
    "email": "jane.oberbrunner+sampleuser@killrvideo.com",
    "firstName": "Jane",
    "lastName": "Oberbrunner"
  },
  {
    "userId": "5ff9758b-534a-402d-9069-4912a1249066",
    "createdDate": "2015-08-31 08:00:02-0600",
    "email": "jermain.rodriguez+sampleuser@killrvideo.com",
    "firstName": "Jermain",
    "lastName": "Rodriguez"
  },
  {
    "userId": "98394fdc-6501-4321-9667-64d1ffe00cfd",
    "createdDate": "2015-08-13 10:00:01-0600",
    "email": "emma.schroeder+sampleuser@killrvideo.com",
    "firstName": "Emma",
    "lastName": "Schroeder"
  },
  {
    "userId": "45c23913-12f2-4e85-9fb8-23dc2fd26aa5",
    "createdDate": "2015-09-06 20:00:02-0600",
    "email": "donatogottlieb+sampleuser@killrvideo.com",
    "firstName": "Donato",
    "lastName": "Gottlieb"
  },
  {
    "userId": "b1fa3fa4-aee8-4d84-9caa-252fd35688af",
    "createdDate": "2015-08-31 16:00:01-0600",
    "email": "bernard_bogan+sampleuser@killrvideo.com",
    "firstName": "Bernard",
    "lastName": "Bogan"
  },
  {
    "userId": "e6774c59-c61c-4276-9d65-50b08c4f43d7",
    "createdDate": "2015-09-07 12:00:01-0600",
    "email": "hertha.jenkins+sampleuser@killrvideo.com",
    "firstName": "Hertha",
    "lastName": "Jenkins"
  },
  {
    "userId": "e3ce573d-bbd3-49bd-8c35-136d22ea2bf9",
    "createdDate": "2015-09-14 12:00:33-0600",
    "email": "rowland.keeling+sampleuser@killrvideo.com",
    "firstName": "Rowland",
    "lastName": "Keeling"
  },
  {
    "userId": "d3d801b5-5d80-41bf-9d76-6d2028411cd0",
    "createdDate": "2015-09-16 14:00:02-0600",
    "email": "louie_grant+sampleuser@killrvideo.com",
    "firstName": "Louie",
    "lastName": "Grant"
  },
  {
    "userId": "97408e07-4de7-4b3f-aaf6-eb75faa91e5a",
    "createdDate": "2015-06-01 18:38:11-0600",
    "email": "brianhauck+sampleuser@killrvideo.com",
    "firstName": "Brian",
    "lastName": "Hauck"
  },
  {
    "userId": "cd154bb6-b5e5-4a0d-bc4a-f1435f6a2462",
    "createdDate": "2015-09-05 08:00:01-0600",
    "email": "breana.keeling+sampleuser@killrvideo.com",
    "firstName": "Breana",
    "lastName": "Keeling"
  },
  {
    "userId": "4453af86-83f0-41d9-a960-87c8100b6a33",
    "createdDate": "2015-08-28 14:06:11-0600",
    "email": "neldarohan+sampleuser@killrvideo.com",
    "firstName": "Nelda",
    "lastName": "Rohan"
  },
  {
    "userId": "1e2f0c4c-b54c-4ef4-97c3-d93e90b9be43",
    "createdDate": "2015-09-07 14:00:01-0600",
    "email": "domenick.rogahn+sampleuser@killrvideo.com",
    "firstName": "Domenick",
    "lastName": "Rogahn"
  }
]